leen/__init__.py
leen/test.py
leen-0.0.1.dist-info/LICENSE.txt
leen-0.0.1.dist-info/METADATA
leen-0.0.1.dist-info/WHEEL
leen-0.0.1.dist-info/top_level.txt
leen-0.0.1.dist-info/RECORD
