Metadata-Version: 2.1
Name: leen
Version: 0.0.1
Summary: A package to judge whether a EBI code correspond to a sentence
Home-page: https://gitlab.com/BioAI/leen
Author: Zhang Zai
Author-email: zhangzai1998@126.com
License: UNKNOWN
Platform: UNKNOWN
Classifier: Programming Language :: Python :: 3
Classifier: License :: OSI Approved :: MIT License
Classifier: Operating System :: OS Independent
